msbench_utils/__init__.py
msbench_utils/cli.py
msbench_utils/reporter.py
msbench_utils-0.0.2.dist-info/entry_points.txt
msbench_utils-0.0.2.dist-info/WHEEL
msbench_utils-0.0.2.dist-info/METADATA
msbench_utils-0.0.2.dist-info/RECORD
